ibats_utils/__init__.py
ibats_utils/compare.py
ibats_utils/db.py
ibats_utils/decorators.py
ibats_utils/iter.py
ibats_utils/json.py
ibats_utils/math.py
ibats_utils/mess.py
ibats_utils/os.py
ibats_utils/pandas.py
ibats_utils/path.py
ibats_utils/redis.py
ibats_utils/transfer.py
ibats_utils/test_case/__init__.py
ibats_utils/test_case/test_db.py
ibats_utils/test_case/test_mess.py
scripts/__init__.py
IBATS_Utils-1.20211214.0.dist-info/LICENSE
IBATS_Utils-1.20211214.0.dist-info/METADATA
IBATS_Utils-1.20211214.0.dist-info/WHEEL
IBATS_Utils-1.20211214.0.dist-info/top_level.txt
IBATS_Utils-1.20211214.0.dist-info/RECORD
