Metadata-Version: 2.1
Name: IBATS-Utils
Version: 1.20211214.0
Summary: IBATS 通用工具，该工具涉及数据库、量化、以及一些通用工具
Home-page: https://github.com/IBATS/IBATS_Utils
Author: MG
Author-email: mmmaaaggg@163.com
License: UNKNOWN
Platform: UNKNOWN
Classifier: Programming Language :: Python :: 3 :: Only
Classifier: Programming Language :: Python :: 3.6
Classifier: Programming Language :: Python :: 3.7
Classifier: Operating System :: Microsoft :: Windows
Classifier: Operating System :: Unix
Classifier: Operating System :: POSIX
Classifier: License :: OSI Approved :: MIT License
Classifier: Development Status :: 5 - Production/Stable
Classifier: Environment :: No Input/Output (Daemon)
Classifier: Intended Audience :: Developers
Classifier: Natural Language :: Chinese (Simplified)
Classifier: Topic :: Software Development
Requires-Python: >=3.6
Requires-Dist: pandas (>=0.24.0)
Requires-Dist: redis (>=2.10.6)
Requires-Dist: SQLAlchemy (>=1.2.8)
Requires-Dist: xlrd (>=1.1.0)
Requires-Dist: matplotlib (>=3.0.3)
Requires-Dist: numba (<=0.52.0,>=0.51.2)
Requires-Dist: simplejson (>=3.17.2)
Requires-Dist: numpy (>=1.18.5)
